trivium-verilog/iverilog/trivium.v
module trivium(output s, input [80:1] IV, KEY, input rst, clk);

    // declare main shift registers
    reg [93:1] srs93;
    reg [84:1] srs84;
    reg [111:1] srs111;

    wire t1, t2, t3;
    integer i;

    // random output
    assign t1 = srs93[66] ^ srs93[93];
    assign t2 = srs84[69] ^ srs84[84];
    assign t3 = srs111[66] ^ srs111[111];

    assign s = t1 ^ t2 ^ t3;

    always @(posedge rst or posedge clk) begin
        if (rst) begin
            $display("Initialization.");
            srs93   = {13'b0, KEY};
            srs84   = {4'b0, IV};
            srs111  = {3'b111, 108'b0 };

            for(i = 0; i < 4*288; i = i + 1) begin
                srs93   = {srs93[92:1], (srs111[66] ^ srs111[111] ^ (srs111[109] & srs111[110]) ^ srs93[69])};
                srs84   = {srs84[83:1], (srs93[66] ^ srs93[93] ^ (srs93[91] & srs93[92]) ^ srs84[78])};
                srs111  = {srs111[110:1], (srs84[69] ^ srs84[84] ^ (srs84[82] & srs84[83]) ^ srs111[87])};
            end
            $display("Initialization finished.");
        end
        else begin
            srs93   = {srs93[92:1], (srs111[66] ^ srs111[111] ^ (srs111[109] & srs111[110]) ^ srs93[69])};
            srs84   = {srs84[83:1], (srs93[66] ^ srs93[93] ^ (srs93[91] & srs93[92]) ^ srs84[78])};
            srs111  = {srs111[110:1], (srs84[69] ^ srs84[84] ^ (srs84[82] & srs84[83]) ^ srs111[87])};
        end
    end

endmodule

trivium-verilog/iverilog/trivium_tb.v
module trivium_tb;

    wire s;
    reg [80:1] key, iv;
    reg rst, clk;

    integer t;

    trivium triv(s, iv, key, rst, clk);

    initial begin
        $dumpfile("test.vcd");
	$dumpvars(0, s);
        key = 80'b0;
        iv = 80'b0;
        rst = 1;
        clk = 0;
        #2 rst = 0;
    end

    always
        #2 clk = ~clk;

    initial begin
        for (t = 1; t <= 32; t = t + 1)
            #2 $display("%d:%d", t, s);
    end
endmodule

trivium-verilog/iverilog/test.vcd
$date
	Fri Mar 18 19:37:47 2022
$end
$version
	Icarus Verilog
$end
$timescale
	1s
$end
$scope module trivium_tb $end
$var wire 1 ! s $end
$upscope $end
$enddefinitions $end
#0
$dumpvars
0!
$end
#2
1!
#6
0!
#38
1!
#42
0!
#46
1!
#54
0!
#66
1!
#70
0!
#82
1!
#94
0!
#98
1!
#114
0!
#122
1!
#130
0!
#138
1!
#150
0!
#154
1!
#170
0!
#174
1!
#186
0!
#190
1!
#202
0!
#222
1!
#226
0!
#230
1!
#242
0!
#246
1!
#266
0!
#278
1!
#286
0!
#290
1!
#294
0!
#306
1!
#310
0!
#314
1!
#322
0!
#326
1!
#334
0!
#338
1!
#346
0!
#366
1!
#370
0!
#374
1!
#378
0!
#386
1!
#402
0!
#406
1!
#410
0!
#418
1!
#422
0!
#426
1!
#434
0!
#454
1!
#466
0!
#478
1!
#486
0!
#498
1!
#518
0!
#522
1!
#530
0!
#538
1!
#550
0!
#554
1!
#558
0!
#566
1!
#570
0!
#582
1!
#590
0!
#594
1!
#606
0!
#610
1!
#630
0!
#634
1!
#638
0!
#650
1!
#654
0!
#658
1!
#678
0!
#682
1!
#694
0!
#698
1!
#702
0!
#718
1!
#734
0!
#738
1!
#754
0!
#766
1!
#770
0!
#774
1!
#786
0!
#802
1!
#814
0!
#818
1!
#830
0!
#842
1!
#846
0!
#854
1!
#862
0!
#870
1!
#894
0!
#906
1!
#926
0!
#934
1!
#942
0!
#946
1!
#958
0!
#970
1!
#986
0!
#990
1!
#998
0!
#1018
1!
#1034
0!
#1038
1!
#1042
0!
#1046
1!
#1050
0!
#1058
1!
#1066
0!
#1074
1!
#1078
0!
#1090
1!
#1098
0!
#1106
1!
#1110
0!
#1122
1!
#1126
0!
#1130
1!
#1138
0!
#1146
1!
#1150
0!
#1162
1!
#1178
0!
#1182
1!
#1186
0!
#1190
1!
#1194
0!
#1198
1!
#1206
0!
#1222
1!
#1230
0!
#1234
1!
#1242
0!
#1246
1!
#1254
0!
#1258
1!
#1262
0!
#1282
1!
#1290
0!
#1294
1!
#1302
0!
#1306
1!
#1310
0!
#1330
1!
#1338
0!
#1346
1!
#1354
0!
#1358
1!
#1366
0!
#1374
1!
#1378
0!
#1390
1!
#1394
0!
#1398
1!
#1406
0!
#1426
1!
#1446
0!
#1450
1!
#1454
0!
#1458
1!
#1462
0!
#1478
1!
#1482
0!
#1494
1!
#1522
0!
#1538
1!
#1542
0!
#1546
1!
#1562
0!
#1566
1!
#1570
0!
#1578
1!
#1582
0!
#1586
1!
#1590
0!
#1594
1!
#1614
0!
#1638
1!
#1654
0!
#1658
1!
#1662
0!
#1670
1!
#1674
0!
#1686
1!
#1702
0!
#1710
1!
#1714
0!
#1718
1!
#1726
0!
#1730
1!
#1734
0!
#1742
1!
#1758
0!
#1778
1!
#1790
0!
#1794
1!
#1802
0!
#1806
1!
#1818
0!
#1826
1!
#1830
0!
#1838
1!
#1846
0!
#1854
1!
#1862
0!
#1866
1!
#1874
0!
#1878
1!
#1882
0!
#1898
1!
#1914
0!
#1918
1!
#1926
0!
#1938
1!
#1942
0!
#1946
1!
#1950
0!
#1970
1!
#1974
0!
#1986
1!
#1990
0!
#2022
1!
#2026
0!
#2034
1!
#2042
0!
#2046
1!
#2058
0!
#2082
1!
#2098
0!
#2102
1!
#2106
0!
#2114
1!
#2118
0!
#2126
1!
#2130
0!
#2134
1!
#2138
0!
#2154
1!
#2158
0!
#2162
1!
#2166
0!
#2170
1!
#2178
0!
#2182
1!
#2190
0!
#2194
1!
#2198
0!
#2206
1!
#2210
0!
#2214
1!
#2222
0!
#2226
1!
#2230
0!
#2234
1!
#2238
0!
#2242
1!
#2254
0!
#2258
1!
#2262
0!
#2270
1!
#2274
0!
#2278
1!
#2282
0!
#2290
1!
#2294
0!
#2306
1!
#2310
0!
#2326
1!
#2330
0!
#2334
1!
#2338
0!
#2346
1!
#2350
0!
#2354
1!
#2362
0!
#2370
1!
#2374
0!
#2378
1!
#2386
0!
#2398
1!
#2402
0!
#2406
1!
#2410
0!
#2418
1!
#2426
0!
#2438
1!
#2450
0!
#2454
1!
#2458
0!
#2470
1!
#2478
0!
#2482
1!
#2490
0!
#2494
1!
#2506
0!
#2522
1!
#2534
0!
#2558
1!
#2562
0!
#2566
1!
#2570
0!
#2586
1!
#2594
0!
#2598
1!
#2606
0!
#2610
1!
#2626
0!
#2630
1!
#2638
0!
#2642
1!
#2646
0!
#2650
1!
#2654
0!
#2674
1!
#2678
0!
#2682
1!
#2686
0!
#2690
1!
#2698
0!
#2702
1!
#2706
0!
#2710
1!
#2714
0!
#2718
1!
#2722
0!
#2730
1!
#2734
0!
#2750
1!
#2762
0!
#2770
1!
#2786
0!
#2790
1!
#2802
0!
#2814
1!
#2822
0!
#2826
1!
#2834
0!
#2838
1!
#2842
0!
#2850
1!
#2858
0!
#2862
1!
#2866
0!
#2882
1!
#2886
0!
#2898
1!
#2902
0!
#2906
1!
#2910
0!
#2918
1!
#2938
0!
#2946
1!
#2954
0!
#2962
1!
#2970
0!
#2974
1!
#2982
0!
#2994
1!
#3010
0!
#3014
1!
#3018
0!
#3026
1!
#3030
0!
#3038
1!
#3054
0!
#3058
1!
#3062
0!
#3074
1!
#3078
0!
#3118
1!
#3122
0!
#3130
1!
#3134
0!
#3146
1!
#3162
0!
#3182
1!
#3186
0!
#3190
1!
#3202
0!
#3206
1!
#3218
0!
#3246
1!
#3250
0!
#3262
1!
#3266
0!
#3270
1!
#3282
0!
#3294
1!
#3298
0!
#3302
1!
#3310
0!
#3318
1!
#3322
0!
#3358
1!
#3370
0!
#3374
1!
#3378
0!
#3382
1!
#3390
0!
#3394
1!
#3398
0!
#3406
1!
#3422
0!
#3426
1!
#3430
0!
#3438
1!
#3442
0!
#3450
1!
#3458
0!
#3470
1!
#3474
0!
#3482
1!
#3490
0!
#3494
1!
#3506
0!
#3510
1!
#3518
0!
#3526
1!
#3530
0!
#3534
1!
#3546
0!
#3582
1!
#3586
0!
#3590
1!
#3594
0!
#3598
1!
#3618
0!
#3630
1!
#3634
0!
#3658
1!
#3662
0!
#3678
1!
#3682
0!
#3690
1!
#3694
0!
#3702
1!
#3710
0!
#3718
1!
#3734
0!
#3738
1!
#3742
0!
#3762
1!
#3766
0!
#3770
1!
#3774
0!
#3778
1!
#3782
0!
#3786
1!
#3802
0!
#3814
1!
#3822
0!
#3834
1!
#3838
0!
#3842
1!
#3854
0!
#3870
1!
#3874
0!
#3878
1!
#3890
0!
#3894
1!
#3898
0!
#3918
1!
#3930
0!
#3938
1!
#3946
0!
#3966
1!
#3974
0!
#3982
1!
#3986
0!
#3994
1!
#4006
0!
#4010
1!
#4018
0!
#4026
1!
#4030
0!
#4034
1!
#4042
0!
#4058
1!
#4062
0!
#4066
1!
#4078
0!
#4086
1!
#4090
0!
#4106
1!
#4114
0!
#4138
1!
#4146
0!
#4150
1!
#4166
0!
#4170
1!
#4182
0!
#4190
1!
#4202
0!
#4210
1!
#4214
0!
#4218
1!
#4226
0!
#4238
1!
#4250
0!
#4258
1!
#4262
0!
#4266
1!
#4270
0!
#4278
1!
#4302
0!
#4326
1!
#4334
0!
#4338
1!
#4346
0!
#4358
1!
#4362
0!
#4366
1!
#4370
0!
#4374
1!
#4386
0!
#4390
1!
#4394
0!
#4398
1!
#4426
0!
#4430
1!
#4434
0!
#4458
1!
#4462
0!
#4466
1!
#4470
0!
#4478
1!
#4482
0!
#4490
1!
#4502
0!
#4514
1!
#4526
0!
#4530
1!
#4534
0!
#4546
1!
#4550
0!
#4558
1!
#4570
0!
#4574
1!
#4578
0!
#4590
1!
#4594
0!
#4598
1!
#4606
0!
#4610
1!
#4650
0!
#4654
1!
#4666
0!
#4670
1!
#4678
0!
#4682
1!
#4686
0!
#4706
1!
#4710
0!
#4714
1!
#4718
0!
#4734
1!
#4738
0!
#4742
1!
#4746
0!
#4750
1!
#4754
0!
#4758
1!
#4762
0!
#4770
1!
#4790
0!
#4806
1!
#4810
0!
#4818
1!
#4822
0!
#4826
1!
#4838
0!
#4842
1!
#4850
0!
#4858
1!
#4862
0!
#4870
1!
#4886
0!
#4906
1!
#4910
0!
#4914
1!
#4922
0!
#4938
1!
#4942
0!
#4946
1!
#4958
0!
#4962
1!
#4970
0!
#4982
1!
#5030
0!
#5038
1!
#5042
0!
#5046
1!
#5062
0!
#5066
1!
#5074
0!
#5094
1!
#5098
0!
#5102
1!
#5106
0!
#5118
1!
#5126
0!
#5134
1!
#5138
0!
#5142
1!
#5154
0!
#5162
1!
#5186
0!
#5202
1!
#5206
0!
#5218
1!
#5226
0!
#5230
1!
#5238
0!
#5246
1!
#5250
0!
#5254
1!
#5258
0!
#5262
1!
#5274
0!
#5278
1!
#5294
0!
#5298
1!
#5306
0!
#5314
1!
#5322
0!
#5326
1!
#5334
0!
#5350
1!
#5358
0!
#5370
1!
#5374
0!
#5382
1!
#5386
0!
#5390
1!
#5398
0!
#5406
1!
#5422
0!
#5434
1!
#5438
0!
#5450
1!
#5454
0!
#5470
1!
#5474
0!
#5486
1!
#5490
0!
#5498
1!
#5502
0!
#5522
1!
#5530
0!
#5534
1!
#5538
0!
#5546
1!
#5554
0!
#5562
1!
#5586
0!
#5590
1!
#5594
0!
#5602
1!
#5606
0!
#5610
1!
#5614
0!
#5618
1!
#5626
0!
#5638
1!
#5646
0!
#5654
1!
#5658
0!
#5666
1!
#5682
0!
#5686
1!
#5694
0!
#5702
1!
#5706
0!
#5710
1!
#5714
0!
#5718
1!
#5726
0!
#5734
1!
#5742
0!
#5746
1!
#5754
0!
#5758
1!
#5782
0!
#5786
1!
#5790
0!
#5798
1!
#5806
0!
#5810
1!
#5814
0!
#5818
1!
#5822
0!
#5826
1!
#5830
0!
#5834
1!
#5850
0!
#5854
1!
#5858
0!
#5866
1!
#5878
0!
#5894
1!
#5898
0!
#5902
1!
#5906
0!
#5914
1!
#5922
0!
#5926
1!
#5930
0!
#5946
1!
#5954
0!
#5958
1!
#5962
0!
#5966
1!
#5982
0!
#5998
1!
#6002
0!
#6022
1!
#6026
0!
#6030
1!
#6038
0!
#6046
1!
#6054
0!
#6074
1!
#6078
0!
#6086
1!
#6090
0!
#6098
1!
#6106
0!
#6110
1!
#6118
0!
#6130
1!
#6138
0!
#6154
1!
#6158
0!
#6178
1!
#6182
0!
#6194
1!
#6198
0!
#6206
1!
#6210
0!
#6218
1!
#6230
0!
#6234
1!
#6242
0!
#6250
1!
#6254
0!
#6266
1!
#6278
0!
#6282
1!
#6290
0!
#6298
1!
#6302
0!
#6322
1!
#6330
0!
#6338
1!
#6354
0!
#6358
1!
#6362
0!
#6370
1!
#6374
0!
#6378
1!
#6382
0!
#6394
1!
#6410
0!
#6422
1!
#6426
0!
#6430
1!
#6438
0!
#6446
1!
#6462
0!
#6466
1!
#6474
0!
#6478
1!
#6482
0!
#6490
1!
#6498
0!
#6510
1!
#6514
0!
#6518
1!
#6522
0!
#6530
1!
#6534
0!
#6538
1!
#6542
0!
#6546
1!
#6554
0!
#6586
1!
#6590
0!
#6602
1!
#6606
0!
#6614
1!
#6622
0!
#6626
1!
#6630
0!
#6638
1!
#6646
0!
#6650
1!
#6662
0!
#6670
1!
#6674
0!
#6686
1!
#6690
0!
#6698
1!
#6706
0!
#6710
1!
#6718
0!
#6726
1!
#6734
0!
#6758
1!
#6762
0!
#6778
1!
#6782
0!
#6786
1!
#6790
0!
#6798
1!
#6802
0!
#6806
1!
#6814
0!
#6818
1!
#6826
0!
#6834
1!
#6838
0!
#6846
1!
#6850
0!
#6854
1!
#6858
0!
#6866
1!
#6874
0!
#6878
1!
#6894
0!
#6906
1!
#6918
0!
#6922
1!
#6934
0!
#6942
1!
#6958
0!
#6962
1!
#6966
0!
#6970
1!
#6974
0!
#6986
1!
#6990
0!
#6998
1!
#7002
0!
#7006
1!
#7014
0!
#7018
1!
#7022
0!
#7026
1!
#7030
0!
#7038
1!
#7046
0!
#7050
1!
#7054
0!
#7062
1!
#7066
0!
#7074
1!
#7082
0!
#7094
1!
#7102
0!
#7106
1!
#7110
0!
#7118
1!
#7126
0!
#7146
1!
#7154
0!
#7158
1!
#7190
0!
#7194
1!
#7202
0!
#7206
1!
#7210
0!
#7214
1!
#7218
0!
#7222
1!
#7230
0!
#7234
1!
#7242
0!
#7246
1!
#7250
0!
#7254
1!
#7258
0!
#7266
1!
#7270
0!
#7274
1!
#7278
0!
#7286
1!
#7302
0!
#7314
1!
#7318
0!
#7334
1!
#7338
0!
#7342
1!
#7354
0!
#7366
1!
#7378
0!
#7386
1!
#7390
0!
#7394
1!
#7402
0!
#7410
1!
#7414
0!
#7434
1!
#7450
0!
#7454
1!
#7458
0!
#7470
1!
#7474
0!
#7478
1!
#7486
0!
#7502
1!
#7510
0!
#7514
1!
#7522
0!
#7534
1!
#7542
0!
#7550
1!
#7554
0!
#7558
1!
#7570
0!
#7578
1!
#7590
0!
#7602
1!
#7606
0!
#7618
1!
#7626
0!
#7642
1!
#7646
0!
#7662
1!
#7666
0!
#7670
1!
#7682
0!
#7686
1!
#7690
0!
#7706
1!
#7718
0!
#7726
1!
#7730
0!
#7738
1!
#7742
0!
#7746
1!
#7750
0!
#7758
1!
#7762
0!
#7766
1!
#7778
0!
#7786
1!
#7790
0!
#7794
1!
#7802
0!
#7806
1!
#7822
0!
#7826
1!
#7830
0!
#7842
1!
#7846
0!
#7850
1!
#7854
0!
#7858
1!
#7870
0!
#7874
1!
#7878
0!
#7882
1!
#7886
0!
#7902
1!
#7914
0!
#7918
1!
#7922
0!
#7926
1!
#7938
0!
#7942
1!
#7946
0!
#7954
1!
#7958
0!
#7970
1!
#7974
0!
#7978
1!
#7982
0!
#7986
1!
#7994
0!
#7998
1!
#8002
0!
#8006
1!
#8014
0!
#8022
1!
#8026
0!
#8030
1!
#8042
0!
#8046
1!
#8054
0!
#8058
1!
#8066
0!
#8070
1!
#8082
0!
#8086
1!
#8090
0!
#8106
1!
#8114
0!
#8118
1!
#8138
0!
#8178
1!
#8186
0!
#8190
1!
#8194
0!
#8198
1!
#8206
0!
#8210
1!
#8214
0!
#8226
1!
#8230
0!
#8238
1!
#8242
0!
#8250
1!
#8254
0!
#8258
1!
#8270
0!
#8278
1!
#8282
0!
#8294
1!
#8298
0!
#8314
1!
#8318
0!
#8322
1!
#8330
0!
#8338
1!
#8354
0!
#8358
1!
#8366
0!
#8378
1!
#8386
0!
#8394
1!
#8402
0!
#8406
1!
#8410
0!
#8414
1!
#8418
0!
#8422
1!
#8442
0!
#8446
1!
#8458
0!
#8462
1!
#8466
0!
#8478
1!
#8486
0!
#8506
1!
#8514
0!
#8518
1!
#8538
0!
#8550
1!
#8554
0!
#8558
1!
#8562
0!
#8570
1!
#8578
0!
#8582
1!
#8586
0!
#8594
1!
#8614
0!
#8618
1!
#8622
0!
#8630
1!
#8642
0!
#8646
1!
#8650
0!
#8662
1!
#8670
0!
#8674
1!
#8678
0!
#8682
1!
#8686
0!
#8690
1!
#8698
0!
#8702
1!
#8718
0!
#8722
1!
#8730
0!
#8746
1!
#8758
0!
#8762
1!
#8766
0!
#8774
1!
#8778
0!
#8790
1!
#8794
0!
#8798
1!
#8810
0!
#8814
1!
#8834
0!
#8846
1!
#8858
0!
#8862
1!
#8870
0!
#8874
1!
#8882
0!
#8886
1!
#8898
0!
#8918
1!
#8926
0!
#8946
1!
#8954
0!
#8962
1!
#8970
0!
#8974
1!
#8994
0!
#8998
1!
#9002
0!
#9010
1!
#9014
0!
#9018
1!
#9022
0!
#9030
1!
#9034
0!
#9038
1!
#9042
0!
#9046
1!
#9058
0!
#9062
1!
#9066
0!
#9078
1!
#9082
0!
#9090
1!
#9094
0!
#9106
1!
#9118
0!
#9122
1!
#9130
0!
#9134
1!
#9138
0!
#9150
1!
#9154
0!
#9158
1!
#9166
0!
#9174
1!
#9178
0!
#9186
1!
#9190
0!
#9198
1!
#9206
0!
#9214
1!
#9226
0!
#9230
1!
#9234
0!
#9246
1!
#9258
0!
#9266
1!
#9274
0!
#9278
1!
#9282
0!
#9290
1!
#9294
0!
#9298
1!
#9302
0!
#9306
1!
#9310
0!
#9314
1!
#9318
0!
#9326
1!
#9334
0!
#9342
1!
#9346
0!
#9358
1!
#9370
0!
#9374
1!
#9378
0!
#9382
1!
#9386
0!
#9390
1!
#9398
0!
#9402
1!
#9406
0!
#9414
1!
#9418
0!
#9422
1!
#9438
0!
#9450
1!
#9454
0!
#9462
1!
#9478
0!
#9482
1!
#9490
0!
#9498
1!
#9502
0!
#9514
1!
#9522
0!
#9534
1!
#9538
0!
#9546
1!
#9554
0!
#9566
1!
#9574
0!
#9582
1!
#9586
0!
#9598
1!
#9610
0!
#9614
1!
#9626
0!
#9630
1!
#9638
0!
#9642
1!
#9646
0!
#9650
1!
#9670
0!
#9678
1!
#9682
0!
#9690
1!
#9698
0!
#9734
1!
#9746
0!
#9762
1!
#9778
0!
#9786
1!
#9794
0!
#9818
1!
#9822
0!
#9838
1!
#9842
0!
#9850
1!
#9854
0!
#9862
1!
#9866
0!
#9878
1!
#9890
0!
#9894
1!
#9898
0!
#9902
1!
#9906
0!
#9910
1!
#9918
0!
#9922
1!
#9938
0!
#9950
1!
#9966
0!
#9970
1!
#9986
0!
#9998
1!
#10006
0!
#10018
1!
#10026
0!
#10038
1!
#10046
0!
#10054
1!
#10058
0!
#10066
1!
#10070
0!
#10078
1!
#10086
0!
#10090
1!
#10094
0!
#10102
1!
#10106
0!
#10118
1!
#10126
0!
#10138
1!
#10142
0!
#10158
1!
#10162
0!
#10174
1!
#10178
0!
#10182
1!
#10186
0!
#10190
1!
#10194
0!
#10206
1!
#10210
0!
#10214
1!
#10222
0!
#10230
1!
#10234
0!
#10238
1!
#10246
0!
#10258
1!
#10278
0!
#10282
1!
#10294
0!
#10298
1!
#10310
0!
#10322
1!
#10326
0!
#10330
1!
#10346
0!
#10350
1!
#10358
0!
#10374
1!
#10386
0!
#10394
1!
#10398
0!
#10402
1!
#10406
0!
#10422
1!
#10438
0!
#10442
1!
#10462
0!
#10466
1!
#10470
0!
#10474
1!
#10478
0!
#10494
1!
#10502
0!
#10506
1!
#10514
0!
#10518
1!
#10526
0!
#10530
1!
#10534
0!
#10546
1!
#10550
0!
#10554
1!
#10558
0!
#10566
1!
#10570
0!
#10574
1!
#10586
0!
#10590
1!
#10594
0!
#10602
1!
#10606
0!
#10614
1!
#10626
0!
#10630
1!
#10634
0!
#10638
1!
#10642
0!
#10646
1!
#10650
0!
#10666
1!
#10670
0!
#10678
1!
#10690
0!
#10706
1!
#10726
0!
#10742
1!
#10746
0!
#10754
1!
#10766
0!
#10770
1!
#10778
0!
#10790
1!
#10794
0!
#10798
1!
#10802
0!
#10830
1!
#10834
0!
#10850
1!
#10854
0!
#10858
1!
#10862
0!
#10866
1!
#10870
0!
#10874
1!
#10886
0!
#10910
1!
#10926
0!
#10930
1!
#10938
0!
#10958
1!
#10966
0!
#10982
1!
#10994
0!
#11014
1!
#11018
0!
#11022
1!
#11026
0!
#11030
1!
#11034
0!
#11038
1!
#11042
0!
#11046
1!
#11050
0!
#11070
1!
#11074
0!
#11110
1!
#11114
0!
#11118
1!
#11122
0!
#11126
1!
#11130
0!
#11134
1!
#11142
0!
#11150
1!
#11158
0!
#11162
1!
#11166
0!
#11178
1!
#11198
0!
#11206
1!
#11218
0!
#11222
1!
#11226
0!
#11234
1!
#11238
0!
#11242
1!
#11250
0!
#11258
1!
#11274
0!
#11278
1!
#11286
0!
#11294
1!
#11302
0!
#11306
1!
#11314
0!
#11318
1!
#11322
0!
#11326
1!
#11330
0!
#11338
1!
#11342
0!
#11346
1!
#11358
0!
#11370
1!
#11374
0!
#11378
1!
#11386
0!
#11390
1!
#11398
0!
#11410
1!
#11442
0!
#11446
1!
#11454
0!
#11458
1!
#11462
0!
#11466
1!
#11470
0!
#11494
1!
#11498
0!
#11502
1!
#11506
0!
#11510
1!
#11514
0!
#11518
1!
#11522
0!
#11526
1!
#11534
0!
#11538
1!
#11542
0!
#11546
1!
#11550
0!
#11558
1!
#11562
0!
#11578
1!
#11582
0!
#11586
1!
#11598
0!
#11602
1!
#11606
0!
#11614
1!
#11618
0!
#11626
1!
#11630
0!
#11634
1!
#11642
0!
#11646
1!
#11658
0!
#11662
1!
#11666
0!
#11674
1!
#11686
0!
#11690
1!
#11694
0!
#11698
1!
#11702
0!
#11706
1!
#11710
0!
#11714
1!
#11718
0!
#11722
1!
#11726
0!
#11730
1!
#11738
0!
#11742
1!
#11746
0!
#11750
1!
#11774
0!
#11778
1!
#11786
0!
#11794
1!
#11802
0!
#11814
1!
#11818
0!
#11822
1!
#11830
0!
#11834
1!
#11854
0!
#11858
1!
#11870
0!
#11878
1!
#11882
0!
#11886
1!
#11894
0!
#11902
1!
#11906
0!
#11910
1!
#11914
0!
#11922
1!
#11926
0!
#11930
1!
#11934
0!
#11938
1!
#11942
0!
#11946
1!
#11962
0!
#11974
1!
#11978
0!
#11986
1!
#11990
0!
#11994
1!
#12002
0!
#12006
1!
#12010
0!
#12018
1!
#12022
0!
#12030
1!
#12038
0!
#12042
1!
#12054
0!
#12058
1!
#12062
0!
#12070
1!
#12078
0!
#12098
1!
#12110
0!
#12114
1!
#12122
0!
#12126
1!
#12150
0!
#12154
1!
#12158
0!
#12162
1!
#12170
0!
#12174
1!
#12178
0!
#12186
1!
#12190
0!
#12202
1!
#12210
0!
#12222
1!
#12230
0!
#12234
1!
#12238
0!
#12246
1!
#12250
0!
#12254
1!
#12258
0!
#12262
1!
#12266
0!
#12278
1!
#12286
0!
#12290
1!
#12294
0!
#12306
1!
#12314
0!
#12326
1!
#12338
0!
#12350
1!
#12354
0!
#12362
1!
#12366
0!
#12374
1!
#12382
0!
#12390
1!
#12394
0!
#12402
1!
#12410
0!
#12414
1!
#12418
0!
#12422
1!
#12426
0!
#12434
1!
#12442
0!
#12446
1!
#12450
0!
#12458
1!
#12462
0!
#12466
1!
#12478
0!
#12482
1!
#12486
0!
#12490
1!
#12498
0!
#12502
1!
#12514
0!
#12518
1!
#12526
0!
#12534
1!
#12546
0!
#12566
1!
#12570
0!
#12578
1!
#12590
0!
#12606
1!
#12610
0!
#12614
1!
#12626
0!
#12630
1!
#12638
0!
#12646
1!
#12658
0!
#12666
1!
#12670
0!
#12678
1!
#12682
0!
#12706
1!
#12710
0!
#12718
1!
#12722
0!
#12726
1!
#12734
0!
#12738
1!
#12742
0!
#12754
1!
#12758
0!
#12762
1!
#12770
0!
#12774
1!
#12778
0!
#12782
1!
#12786
0!
#12794
1!
#12802
0!
#12818
1!
#12822
0!
#12826
1!
#12830
0!
#12846
1!
#12874
0!
#12878
1!
#12882
0!
#12894
1!
#12906
0!
#12910
1!
#12918
0!
#12938
1!
#12946
0!
#12950
1!
#12954
0!
#12958
1!
#12962
0!
#12966
1!
#12970
0!
#12978
1!
#12986
0!
#12994
1!
#13010
0!
#13018
1!
#13030
0!
#13038
1!
#13050
0!
#13054
1!
#13058
0!
#13062
1!
#13066
0!
#13070
1!
#13074
0!
#13078
1!
#13090
0!
#13110
1!
#13114
0!
#13118
1!
#13122
0!
#13130
1!
#13138
0!
#13154
1!
#13158
0!
#13170
1!
#13174
0!
#13178
1!
#13182
0!
#13186
1!
#13194
0!
#13210
1!
#13226
0!
#13230
1!
#13234
0!
#13250
1!
#13254
0!
#13262
1!
#13274
0!
#13286
1!
#13294
0!
#13298
1!
#13338
0!
#13342
1!
#13354
0!
#13358
1!
#13378
0!
#13386
1!
#13398
0!
#13418
1!
#13422
0!
#13426
1!
#13430
0!
#13438
1!
#13446
0!
#13454
1!
#13458
0!
#13466
1!
#13478
0!
#13502
1!
#13510
0!
#13526
1!
#13530
0!
#13534
1!
#13550
0!
#13554
1!
#13558
0!
#13562
1!
#13566
0!
#13586
1!
#13606
0!
#13610
1!
#13618
0!
#13642
1!
#13646
0!
#13650
1!
#13654
0!
#13658
1!
#13674
0!
#13678
1!
#13686
0!
#13706
1!
#13714
0!
#13738
1!
#13742
0!
#13746
1!
#13750
0!
#13758
1!
#13762
0!
#13770
1!
#13782
0!
#13790
1!
#13794
0!
#13798
1!
#13810
0!
#13818
1!
#13830
0!
#13838
1!
#13842
0!
#13846
1!
#13858
0!
#13874
1!
#13878
0!
#13882
1!
#13890
0!
#13898
1!
#13902
0!
#13918
1!
#13930
0!
#13934
1!
#13954
0!
#13982
1!
#13998
0!
#14002
1!
#14006
0!
#14018
1!
#14022
0!
#14026
1!
#14030
0!
#14034
1!
#14042
0!
#14058
1!
#14062
0!
#14070
1!
#14094
0!
#14114
1!
#14126
0!
#14130
1!
#14142
0!
#14150
1!
#14154
0!
#14158
1!
#14166
0!
#14178
1!
#14186
0!
#14202
1!
#14206
0!
#14210
1!
#14218
0!
#14222
1!
#14230
0!
#14238
1!
#14250
0!
#14262
1!
#14266
0!
#14286
1!
#14290
0!
#14294
1!
#14302
0!
#14310
1!
#14314
0!
#14318
1!
#14326
0!
#14330
1!
#14346
0!
#14350
1!
#14354
0!
#14362
1!
#14374
0!
#14382
1!
#14394
0!
#14402
1!
#14410
0!
#14418
1!
#14430
0!
#14434
1!
#14438
0!
#14450
1!
#14454
0!
#14462
1!
#14466
0!
#14470
1!
#14474
0!
#14482
1!
#14494
0!
#14502
1!
#14510
0!
#14514
1!
#14518
0!
#14526
1!
#14530
0!
#14534
1!
#14542
0!
#14546
1!
#14550
0!
#14554
1!
#14562
0!
#14566
1!
#14574
0!
#14578
1!
#14614
0!
#14618
1!
#14626
0!
#14630
1!
#14642
0!
#14646
1!
#14654
0!
#14662
1!
#14666
0!
#14670
1!
#14674
0!
#14682
1!
#14686
0!
#14694
1!
#14710
0!
#14714
1!
#14726
0!
#14734
1!
#14746
0!
#14750
1!
#14762
0!
#14766
1!
#14786
0!
#14798
1!
#14830
0!
#14838
1!
#14842
0!
#14850
1!
#14858
0!
#14866
1!
#14882
0!
#14886
1!
#14890
0!
#14898
1!
#14902
0!
#14906
1!
#14918
0!
#14922
1!
#14934
0!
#14938
1!
#14950
0!
#14958
1!
#14962
0!
#14966
1!
#14994
0!
#15002
1!
#15006
0!
#15014
1!
#15018
0!
#15026
1!
#15030
0!
#15034
1!
#15038
0!
#15050
1!
#15058
0!
#15066
1!
#15074
0!
#15078
1!
#15090
0!
#15106
1!
#15110
0!
#15134
1!
#15138
0!
#15142
1!
#15146
0!
#15150
1!
#15158
0!
#15162
1!
#15170
0!
#15174
1!
#15182
0!
#15186
1!
#15190
0!
#15194
1!
#15206
0!
#15210
1!
#15214
0!
#15218
1!
#15226
0!
#15230
1!
#15238
0!
#15242
1!
#15246
0!
#15250
1!
#15254
0!
#15262
1!
#15266
0!
#15282
1!
#15286
0!
#15290
1!
#15294
0!
#15302
1!
#15306
0!
#15314
1!
#15338
0!
#15354
1!
#15374
0!
#15382
1!
#15386
0!
#15394
1!
#15398
0!
#15402
1!
#15410
0!
#15418
1!
#15422
0!
#15434
1!
#15442
0!
#15446
1!
#15462
0!
#15474
1!
#15478
0!
#15482
1!
#15486
0!
#15490
1!
#15494
0!
#15506
1!
#15510
0!
#15530
1!
#15542
0!
#15546
1!
#15554
0!
#15562
1!
#15574
0!
#15586
1!
#15590
0!
#15602
1!
#15606
0!
#15610
1!
#15618
0!
#15622
1!
#15626
0!
#15638
1!
#15642
0!
#15650
1!
#15662
0!
#15666
1!
#15674
0!
#15678
1!
#15682
0!
#15698
1!
#15702
0!
#15706
1!
#15710
0!
#15726
1!
#15730
0!
#15734
1!
#15746
0!
#15758
1!
#15782
0!
#15786
1!
#15790
0!
#15794
1!
#15798
0!
#15802
1!
#15806
0!
#15814
1!
#15818
0!
#15822
1!
#15826
0!
#15834
1!
#15842
0!
#15846
1!
#15854
0!
#15858
1!
#15866
0!
#15874
1!
